casher.py
casher-0.5.0.dist-info/LICENSE.rst
casher-0.5.0.dist-info/WHEEL
casher-0.5.0.dist-info/METADATA
casher-0.5.0.dist-info/RECORD
